optimal_mean_estimator/__init__.py
optimal_mean_estimator/optimalmean.py
optimal_mean_estimator-2.0.0.dist-info/LICENSE
optimal_mean_estimator-2.0.0.dist-info/METADATA
optimal_mean_estimator-2.0.0.dist-info/WHEEL
optimal_mean_estimator-2.0.0.dist-info/top_level.txt
optimal_mean_estimator-2.0.0.dist-info/RECORD
