Metadata-Version: 2.1
Name: optimal_mean_estimator
Version: 2.0.0
Summary: a Python implementation of the optimal subgaussian mean estimator that was published by Lee and Valiant at https://arxiv.org/abs/2011.08384
Home-page: https://github.com/bschulz81/optimal_mean_estimator/tree/main
Author: Benjamin Schulz
License: MIT License
Keywords: statistics,estimator,mean
Classifier: Programming Language :: Python :: 3
Classifier: License :: OSI Approved :: MIT License
Classifier: Operating System :: OS Independent
Requires-Python: >=3.7
License-File: LICENSE
Requires-Dist: numpy
Requires-Dist: scipy
